latex_gen_pro_py/__init__.py
latex_gen_pro_py/tex.py
latex_gen_pro_py-0.0.1.dist-info/METADATA
latex_gen_pro_py-0.0.1.dist-info/WHEEL
latex_gen_pro_py-0.0.1.dist-info/top_level.txt
latex_gen_pro_py-0.0.1.dist-info/RECORD
